<?xml version="1.0" encoding="utf-8" ?>
<dwsync>
<file name="note_dead.jpg" server="31.220.16.124" local="130485361914668201" remote="130484371200000000" Dst="2" />
<file name="note_flash.gif" server="31.220.16.124" local="130485361940409674" remote="130484371200000000" Dst="2" />
<file name="note_still.jpg" server="31.220.16.124" local="130485362028184694" remote="130484371200000000" Dst="2" />
<file name="pmStill.gif" server="31.220.16.124" local="130485362036575174" remote="130484371200000000" Dst="2" />
<file name="avatardefault.jpg" server="31.220.16.124" local="130484371200000000" remote="130484371200000000" Dst="2" />
<file name="gLogo.jpg" server="31.220.16.124" local="130484371200000000" remote="130484371200000000" Dst="2" />
<file name="group3.png" server="31.220.16.124" local="130484371200000000" remote="130484371200000000" Dst="2" />
<file name="home.png" server="31.220.16.124" local="130484371200000000" remote="130484371200000000" Dst="2" />
<file name="logo.png" server="31.220.16.124" local="130484371200000000" remote="130484371200000000" Dst="2" />
<file name="magnify_glass.png" server="31.220.16.124" local="130484371200000000" remote="130484371200000000" Dst="2" />
<file name="pmFlash.gif" server="31.220.16.124" local="130484371200000000" remote="130484371200000000" Dst="2" />
</dwsync>